dlh_utils/__init__.py
dlh_utils/_version.py
dlh_utils/dataframes.py
dlh_utils/disco.py
dlh_utils/flags.py
dlh_utils/formatting.py
dlh_utils/linkage.py
dlh_utils/profiling.py
dlh_utils/sessions.py
dlh_utils/standardisation.py
dlh_utils/tests/__init__.py
dlh_utils/tests/conftest.py
dlh_utils/tests/test_dataframes.py
dlh_utils/tests/test_flags.py
dlh_utils/tests/test_formatting.py
dlh_utils/tests/test_linkage.py
dlh_utils/tests/test_profiling.py
dlh_utils/tests/test_standardisation.py
dlh_utils/tests/test_utilities.py
dlh_utils/utilities.py
dlh_utils-0.4.1.dist-info/LICENSE
dlh_utils-0.4.1.dist-info/METADATA
dlh_utils-0.4.1.dist-info/WHEEL
dlh_utils-0.4.1.dist-info/RECORD
