Metadata-Version: 2.1
Name: dlh_utils
Version: 0.4.1
Summary: A PySpark package used to expedite and standardise the data linkage process
Home-page: https://github.com/Data-Linkage/dlh_utils
License: MIT
Author: ONS Data Linkage Hub
Author-email: linkage.hub@ons.gov.uk
Requires-Python: >=3.6.8
Classifier: License :: OSI Approved :: MIT License
Classifier: Programming Language :: Python :: 3
Classifier: Programming Language :: Python :: 3.7
Classifier: Programming Language :: Python :: 3.8
Classifier: Programming Language :: Python :: 3.9
Classifier: Programming Language :: Python :: 3.10
Classifier: Programming Language :: Python :: 3.11
Classifier: Programming Language :: Python :: 3.12
Requires-Dist: graphframes (>=0.6,<0.7)
Requires-Dist: graphframes-jars (>=0.5,<0.6)
Requires-Dist: importlib_metadata (>=4.8.3,<5.0.0)
Requires-Dist: jellyfish (>=0.9,<0.10)
Requires-Dist: numpy (>=1.15.4)
Requires-Dist: pandas (>=0.20.3)
Project-URL: Repository, https://github.com/Data-Linkage/dlh_utils
